.gitignore
CHANGES.rst
CONTRIBUTORS.txt
MANIFEST.in
README.txt
TODO.txt
__init__.py
bootstrap.py
buildout.cfg
setup.cfg
setup.py
src/__init__.py
src/uwosh/__init__.py
src/uwosh.transitionbuttons.egg-info/PKG-INFO
src/uwosh.transitionbuttons.egg-info/SOURCES.txt
src/uwosh.transitionbuttons.egg-info/dependency_links.txt
src/uwosh.transitionbuttons.egg-info/entry_points.txt
src/uwosh.transitionbuttons.egg-info/namespace_packages.txt
src/uwosh.transitionbuttons.egg-info/not-zip-safe
src/uwosh.transitionbuttons.egg-info/requires.txt
src/uwosh.transitionbuttons.egg-info/top_level.txt
src/uwosh/transitionbuttons/__init__.py
src/uwosh/transitionbuttons/adapter.py
src/uwosh/transitionbuttons/configure.zcml
src/uwosh/transitionbuttons/controlpanel.py
src/uwosh/transitionbuttons/interfaces.py
src/uwosh/transitionbuttons/overrides.zcml
src/uwosh/transitionbuttons/personalpreferences.py
src/uwosh/transitionbuttons/testing.py
src/uwosh/transitionbuttons/userdataschema.py
src/uwosh/transitionbuttons/Extensions/Install.py
src/uwosh/transitionbuttons/browser/__init__.py
src/uwosh/transitionbuttons/browser/configure.zcml
src/uwosh/transitionbuttons/browser/js_viewlet.pt
src/uwosh/transitionbuttons/browser/viewlets.py
src/uwosh/transitionbuttons/browser/resources/buttons.css
src/uwosh/transitionbuttons/browser/resources/buttons.js
src/uwosh/transitionbuttons/profiles/default/browserlayer.xml
src/uwosh/transitionbuttons/profiles/default/componentregistry.xml
src/uwosh/transitionbuttons/profiles/default/configure.zcml
src/uwosh/transitionbuttons/profiles/default/controlpanel.xml
src/uwosh/transitionbuttons/profiles/default/cssregistry.xml
src/uwosh/transitionbuttons/profiles/default/jsregistry.xml
src/uwosh/transitionbuttons/profiles/default/memberdata_properties.xml
src/uwosh/transitionbuttons/profiles/default/metadata.xml
src/uwosh/transitionbuttons/profiles/default/propertiestool.xml
src/uwosh/transitionbuttons/profiles/default/registry.xml
src/uwosh/transitionbuttons/profiles/uninstall/browserlayer.xml
src/uwosh/transitionbuttons/profiles/uninstall/componentregistry.xml
src/uwosh/transitionbuttons/profiles/uninstall/controlpanel.xml
src/uwosh/transitionbuttons/profiles/uninstall/cssregistry.xml
src/uwosh/transitionbuttons/profiles/uninstall/jsregistry.xml
src/uwosh/transitionbuttons/profiles/uninstall/memberdata_properties.xml
src/uwosh/transitionbuttons/profiles/uninstall/registry.xml
