Metadata-Version: 1.1
Name: uwosh.transitionbuttons
Version: 0.9.75
Summary: Adds a button interface for the different state ttransitions
Home-page: http://svn.plone.org/svn/collective/
Author: UNKNOWN
Author-email: UNKNOWN
License: gpl
Platform: UNKNOWN
Classifier: Environment :: Web Environment
Classifier: Framework :: Plone
Classifier: Operating System :: OS Independent
Classifier: Programming Language :: Python
Classifier: Programming Language :: Python :: 2.6
Classifier: Topic :: Software Development :: Libraries :: Python Modules
